LICENSE
README.rst
ggsheet.py
setup.py
micropython_googlesheet.egg-info/PKG-INFO
micropython_googlesheet.egg-info/SOURCES.txt
micropython_googlesheet.egg-info/dependency_links.txt
micropython_googlesheet.egg-info/top_level.txt