Metadata-Version: 2.1
Name: micropython-googlesheet
Version: 0.0.3
Summary: Update or append the data to Google Sheet, or get the data on Google Sheet. by using HTTP to execute the Google Apps Script API compatible with ESP32 and ESP8266.
Home-page: https://github.com/PerfecXX/MicroPython-GoogleSheet
Author: Teeraphat Kullanankanjana
Author-email: ku.teeraphat@hotmail.com
Maintainer: Teeraphat Kullanankanjana
Maintainer-email: ku.teeraphat@hotmail.com
License: MIT
Keywords: googlesheet,esp32,esp8266,micropython
Platform: UNKNOWN
Classifier: Development Status :: 3 - Alpha
Classifier: Programming Language :: Python :: Implementation :: MicroPython
Classifier: License :: OSI Approved :: MIT License
License-File: LICENSE
